MANIFEST.in
setup.cfg
setup.py
pixiedust_flightpredict/__init__.py
pixiedust_flightpredict/configureTraining.py
pixiedust_flightpredict/createModels.py
pixiedust_flightpredict/flightPredict.py
pixiedust_flightpredict/histogramDisplay.py
pixiedust_flightpredict/mapResults.py
pixiedust_flightpredict/runMetrics.py
pixiedust_flightpredict/vizFeatures.py
pixiedust_flightpredict.egg-info/PKG-INFO
pixiedust_flightpredict.egg-info/SOURCES.txt
pixiedust_flightpredict.egg-info/dependency_links.txt
pixiedust_flightpredict.egg-info/not-zip-safe
pixiedust_flightpredict.egg-info/requires.txt
pixiedust_flightpredict.egg-info/top_level.txt
pixiedust_flightpredict/running/__init__.py
pixiedust_flightpredict/running/flightAccess.py
pixiedust_flightpredict/running/flightHistory.py
pixiedust_flightpredict/running/runModel.py
pixiedust_flightpredict/running/weatherAccess.py
pixiedust_flightpredict/templates/architecture.png
pixiedust_flightpredict/templates/configureWizard.html
pixiedust_flightpredict/templates/flightBadge.html
pixiedust_flightpredict/templates/flightPredict.jpeg
pixiedust_flightpredict/templates/flights.css
pixiedust_flightpredict/templates/flights.html
pixiedust_flightpredict/templates/flights.js
pixiedust_flightpredict/templates/flightsScript.html
pixiedust_flightpredict/templates/histogram.html
pixiedust_flightpredict/templates/mapResults.html
pixiedust_flightpredict/templates/mapResults.js
pixiedust_flightpredict/templates/step_credentials.html
pixiedust_flightpredict/templates/step_sets.html
pixiedust_flightpredict/templates/step_welcome.html
pixiedust_flightpredict/templates/vizFeatures.png
pixiedust_flightpredict/templates/gencode/customHandlers.template
pixiedust_flightpredict/templates/gencode/labeledRDD.template
pixiedust_flightpredict/training/__init__.py
pixiedust_flightpredict/training/training.py