Metadata-Version: 1.0
Name: pixiedust-flightpredict
Version: 0.8
Summary: Flight delay predictor application with PixieDust
Home-page: https://github.com/ibm-cds-labs/simple-data-pipe-connector-flightstats/tree/master/pixiedust_flightpredict
Author: David Taieb
Author-email: david_taieb@us.ibm.com
License: Apache 2.0
Platform: UNKNOWN
